expressionablecli/__init__.py
expressionablecli/__main__.py
expressionablecli/expressionablecli.py
mergecli/__init__.py
mergecli/__main__.py
mergecli/mergecli.py
expressionable_cli-1.2.dist-info/LICENSE
expressionable_cli-1.2.dist-info/METADATA
expressionable_cli-1.2.dist-info/WHEEL
expressionable_cli-1.2.dist-info/entry_points.txt
expressionable_cli-1.2.dist-info/top_level.txt
expressionable_cli-1.2.dist-info/RECORD
