Metadata-Version: 2.1
Name: expressionable-cli
Version: 1.2
Summary: A command-line tool for transforming large data sets
Home-page: https://github.com/srp33/ExpressionAble-CLI
Author: Piccolo Lab
Author-email: stephen_piccolo@byu.edu
License: MIT
Platform: UNKNOWN
Requires-Dist: expressionable (>=1.2)
Requires-Dist: pandas
